Workbook

Sheet README
A1: Truestead Business Brokerage — BOV Recast Workbook
A2: Companion to _internal/BUSINESS-EVALUATION.md. Version 1, 2026-09-12.
A4: How to use
A5: 1 | B5: Fill the blue cells on the Inputs sheet (period labels, weights, multiples, buyer-test assumptions). Yellow cells are the ones that most change the answer.
A6: 2 | B6: Enter the seller's tax-return figures on Recast. Every add-back needs a Y in the Doc? column or it is excluded from SDE automatically.
A7: 3 | B7: Score the Risk Grid. Each adjustment moves the industry multiple; the sheet caps the result between the floor and cap set on Inputs.
A8: 4 | B8: Valuation reconciles the SDE method, the rule-of-thumb/comps midpoint, and the asset floor into an indicated value, a range, and a rounded asking price.
A9: 5 | B9: Buyer Test checks whether a 10%-down SBA buyer with a seller note can cover a market salary and debt service at the target coverage ratio, and solves for the maximum supportable price.
A10: 6 | B10: Screen is the listing-qualification scorecard from the playbook (§1.2). Score 0/1/2 per line; the decision is computed.
A11: Legend
A12: Blue text | B12: Hardcoded input — you type here.
A13: Black text | B13: Formula — do not overwrite.
A14: Green text | B14: Link to another sheet.
A15: Yellow fill | B15: Key assumption; check it on every engagement.
A16: Example data | B16: The workbook ships filled with the invented Ormond Beach HVAC example from the playbook §6 so every formula can be checked. Replace all blue cells before using on a real engagement.
A17: Disclaimer | B17: This workbook supports a Broker Opinion of Value. It is not an appraisal and must not be described as one (F.S. 475.612 / 475.628 for any real-property component). It relies on seller-provided information that has not been audited. Not for lending, tax, or litigation use — SBA-threshold deals, estate/gift tax, and disputes require a credentialed appraiser (see playbook §2.1).

Sheet Inputs
A1: Inputs & Assumptions
A3: Engagement
A4: Business name | B4: Example: Ormond Beach HVAC Co. (invented)
A5: Industry / NAICS | B5: HVAC contractor — NAICS 238220
A6: Valuation date | B6: 2026-09-12
A7: Prepared by | B7: Truestead Business Brokerage
A9: Periods and weights (most recent period weighted highest)
A10: Period label | C10: FY2023 | D10: FY2024 | E10: FY2025 | F10: TTM Aug-2026
A11: Weight | C11: 0.1 | D11: 0.2 | E11: 0.3 | F11: 0.4 | G11: =SUM(C11:F11) -> 1
A12: Weights check (must be 100%) | B12: =IF(ROUND(G11,4)=1,"OK","WEIGHTS DO NOT SUM TO 100%") -> OK
A14: Multiples
A15: Industry median SDE multiple | B15: 2.5
A16: Source cited for the multiple | B16: Illustrative — replace with source and date
A17: Rule-of-thumb multiple — low | B17: 2
A18: Rule-of-thumb multiple — high | B18: 3
A19: Revenue multiple (sanity check only) | B19: 0.45
A20: Adjusted multiple floor | B20: 1
A21: Adjusted multiple cap | B21: 4
A23: Buyer test (SBA 7(a) structure)
A24: Buyer down payment (% of price) | B24: 0.1
A25: Seller note (% of price) | B25: 0.1
A26: Seller note interest rate | B26: 0.07
A27: Seller note term (years) | B27: 5
A28: SBA loan interest rate | B28: 0.105
A29: SBA loan term (years) | B29: 10
A30: Closing costs + working capital financed ($) | B30: 50000
A31: Buyer market salary ($/yr) | B31: 100000
A32: Target debt-service coverage ratio | B32: 1.25
A34: Pricing & reconciliation
A35: Asking-price premium over indicated value | B35: 0.05
A36: Round prices to nearest ($) | B36: 5000
A37: Range half-width (± around indicated value) | B37: 0.075
A38: Weight — SDE method | B38: 0.6
A39: Weight — rule-of-thumb / comps midpoint | B39: 0.3
A40: Weight — asset approach | B40: 0.1
A41: Reconciliation weights check | B41: =IF(ROUND(SUM(B38:B40),4)=1,"OK","WEIGHTS DO NOT SUM TO 100%") -> OK

Sheet Recast
A1: Earnings Recast — Seller's Discretionary Earnings
A2: Enter figures from the business tax returns (not the seller's P&L). Add-backs count only when Doc? = Y.
A3: Line | B3: Doc? | C3: =Inputs!C10 -> FY2023 | D3: =Inputs!D10 -> FY2024 | E3: =Inputs!E10 -> FY2025 | F3: =Inputs!F10 -> TTM Aug-2026 | G3: Weighted | H3: Notes / exhibit reference
A4: Revenue | C4: 1700000 | D4: 1900000 | E4: 2050000 | F4: 2100000 | G4: =SUMPRODUCT(Inputs!$C$11:$F$11,C4:F4) -> 2005000 | H4: Form 1120-S / 1065 line 1a
A5: Net income per tax return | C5: 120000 | D5: 150000 | E5: 170000 | F5: 180000 | G5: =SUMPRODUCT(Inputs!$C$11:$F$11,C5:F5) -> 165000 | H5: Ordinary business income per return
A7: Add-backs (counted only when Doc? = Y)
A8: Owner salary (one owner) | B8: Y | C8: 100000 | D8: 105000 | E8: 110000 | F8: 110000 | H8: W-2 / officer comp schedule
A9: Owner payroll taxes | B9: Y | C9: 7650 | D9: 8033 | E9: 8415 | F9: 8415 | H9: Form 941s
A10: Owner benefits & perks (auto, health, phone) | B10: Y | C10: 22000 | D10: 22000 | E10: 22000 | F10: 22000 | H10: GL detail + policy statements
A11: Interest expense | B11: Y | C11: 9000 | D11: 9000 | E11: 9000 | F11: 9000 | H11: Return, interest line
A12: Depreciation | B12: Y | C12: 48000 | D12: 48000 | E12: 48000 | F12: 48000 | H12: Form 4562
A13: Amortization | B13: Y | C13: 0 | D13: 0 | E13: 0 | F13: 0 | H13: Form 4562
A14: Non-recurring expenses (describe) | B14: Y | C14: 0 | D14: 0 | E14: 15000 | F14: 15000 | H14: Settlement agreement + invoice
A15: Non-cash charges | B15: Y | C15: 0 | D15: 0 | E15: 0 | F15: 0
A16: Personal expenses run through the business | B16: N | C16: 6000 | D16: 6000 | E16: 6000 | F16: 6000 | H16: No receipts produced — EXCLUDED until documented
A17: Other add-back (describe) | B17: Y | C17: 0 | D17: 0 | E17: 0 | F17: 0
A18: Total documented add-backs | C18: =SUMPRODUCT(--($B$8:$B$17="Y"),C8:C17) -> 186650 | D18: =SUMPRODUCT(--($B$8:$B$17="Y"),D8:D17) -> 192033 | E18: =SUMPRODUCT(--($B$8:$B$17="Y"),E8:E17) -> 212415 | F18: =SUMPRODUCT(--($B$8:$B$17="Y"),F8:F17) -> 212415 | G18: =SUMPRODUCT(Inputs!$C$11:$F$11,C18:F18) -> 205762.1
A19: Add-backs excluded for lack of documentation (count) | B19: =SUMPRODUCT(--($B$8:$B$17="N"),--(ABS(C8:C17)+ABS(D8:D17)+ABS(E8:E17)+ABS(F8:F17)>0)) -> 1
A21: Deductions (enter as positive numbers)
A22: Income that will not transfer (rent from excluded property, PPP/ERC, one-time gains) | C22: 0 | D22: 0 | E22: 0 | F22: 0
A23: Replacement cost of a second working owner / unpaid family | C23: 0 | D23: 0 | E23: 0 | F23: 0 | H23: Market wage for the role
A24: Market rent adjustment (market rent − rent actually paid) | C24: 18000 | D24: 18000 | E24: 18000 | F24: 18000 | H24: Related-party lease below market; CMA on file
A25: Other deduction (describe) | C25: 0 | D25: 0 | E25: 0 | F25: 0
A26: Total deductions | C26: =SUM(C22:C25) -> 18000 | D26: =SUM(D22:D25) -> 18000 | E26: =SUM(E22:E25) -> 18000 | F26: =SUM(F22:F25) -> 18000 | G26: =SUMPRODUCT(Inputs!$C$11:$F$11,C26:F26) -> 18000
A28: Result
A29: Seller's Discretionary Earnings (SDE) | C29: =C5+C18-C26 -> 288650 | D29: =D5+D18-D26 -> 324033 | E29: =E5+E18-E26 -> 364415 | F29: =F5+F18-F26 -> 374415 | G29: =SUMPRODUCT(Inputs!$C$11:$F$11,C29:F29) -> 352762.1 | H29: Weighted SDE drives the valuation
A30: SDE margin | C30: =IF(C4=0,0,C29/C4) -> 0.16979412 | D30: =IF(D4=0,0,D29/D4) -> 0.17054368 | E30: =IF(E4=0,0,E29/E4) -> 0.17776341 | F30: =IF(F4=0,0,F29/F4) -> 0.17829286 | G30: =IF(G4=0,0,G29/G4) -> 0.1759412
A31: SDE growth vs. prior period | D31: =IF(C29=0,0,D29/C29-1) -> 0.12258098 | E31: =IF(D29=0,0,E29/D29-1) -> 0.12462311 | F31: =IF(E29=0,0,F29/E29-1) -> 0.027441241
A32: Revenue growth vs. prior period | D32: =IF(C4=0,0,D4/C4-1) -> 0.11764706 | E32: =IF(D4=0,0,E4/D4-1) -> 0.078947368 | F32: =IF(E4=0,0,F4/E4-1) -> 0.024390244
A34: Rules: every add-back has an exhibit; unreported cash gets zero credit; three years plus trailing twelve months, weighted toward the most recent.

Sheet Risk Grid
A1: Multiple Adjustment — Risk Grid
A2: Start from the industry median multiple and move it by each factor. Typical range per factor is −0.30x to +0.30x. Document every move in column D.
A4: Factor | B4: Assessment | C4: Adjustment (x) | D4: Evidence / note
A5: Owner dependence | B5: Manager in place; owner ~35 hrs/wk | C5: 0.1 | D5: Org chart, manager tenure 6 yrs
A6: Size of SDE | B6: Weighted SDE ≈ $350K | C6: 0 | D6: Buyer pool and lender appetite widen above $300K
A7: Trend | B7: Revenue and SDE up 3 years | C7: 0.1 | D7: Recast growth rows
A8: Customer concentration | B8: Largest customer ~8% | C8: 0.05 | D8: Customer sales report
A9: Lease | B9: 6 years remaining, assignable, related-party rent normalized | C9: 0.05 | D9: Lease + amendment; landlord = seller's LLC
A10: Books | B10: Returns reconcile to P&L; deposits tie out | C10: 0.05 | D10: Bank tie-out worksheet
A11: Staff | B11: 8 employees, avg tenure 4 yrs; one senior tech at risk | C11: -0.05 | D11: Payroll register; interview after LOI
A12: Licenses | B12: Seller is the F.S. 489 qualifying agent; will stay 12 months | C12: -0.15 | D12: DBPR license; qualifier plan needed
A13: Assets | B13: Fleet avg 5 yrs, maintained | C13: 0 | D13: Equipment list
A14: Financeability | B14: SBA-eligible; seller will carry 10% note | C14: 0.05 | D14: Lender pre-read
A15: Transition | B15: 12-month transition offered | C15: 0 | D15: Seller interview
A16: Net adjustment | C16: =SUM(C5:C15) -> 0.2
A17: Industry median multiple | C17: =Inputs!B15 -> 2.5
A18: Adjusted multiple (capped between floor and cap) | C18: =MAX(Inputs!B20,MIN(Inputs!B21,C17+C16)) -> 2.7

Sheet Valuation
A1: Valuation — Three Approaches, Reconciliation, Range, Asking Price
A3: Drivers
A4: Weighted SDE | B4: =Recast!$G$29 -> 352762.1
A5: Weighted revenue | B5: =Recast!$G$4 -> 2005000
A6: Adjusted multiple | B6: ='Risk Grid'!$C$18 -> 2.7
A8: Approach 1 — Market: multiple of SDE (primary)
A9: Indicated value — SDE × adjusted multiple | B9: =B4*B6 -> 952457.67
A11: Approach 2 — Market: rule of thumb / comparable transactions
A12: Low (SDE × low multiple) | B12: =B4*Inputs!B17 -> 705524.2
A13: High (SDE × high multiple) | B13: =B4*Inputs!B18 -> 1058286.3
A14: Midpoint | B14: =AVERAGE(B12:B13) -> 881905.25
A15: Revenue-multiple sanity check (not weighted) | B15: =B5*Inputs!B19 -> 902250
A17: Approach 3 — Asset: adjusted net asset value (the floor)
A18: Furniture, fixtures & equipment (fair market value) | B18: 210000
A19: Vehicles (fair market value) | B19: 165000
A20: Accounts receivable (only if transferred) | B20: 95000
A21: Inventory at cost (only if included in price) | B21: 0
A22: Other transferable assets | B22: 0
A23: Less: payables and liabilities assumed by buyer | B23: 60000
A24: Adjusted net asset value | B24: =SUM(B18:B22)-B23 -> 410000
A26: Reconciliation
A27: Weighted indicated value (weights on Inputs) | B27: =B9*Inputs!B38+B14*Inputs!B39+B24*Inputs!B40 -> 877046.18
A28: Indicated value (not below asset floor) | B28: =MAX(B27,B24) -> 877046.18
A30: Range and asking price (rounded)
A31: Most probable selling price — low | B31: =ROUND(B28*(1-Inputs!B37)/Inputs!B36,0)*Inputs!B36 -> 810000
A32: Most probable selling price — high | B32: =ROUND(B28*(1+Inputs!B37)/Inputs!B36,0)*Inputs!B36 -> 945000
A33: Recommended asking price | B33: =ROUND(B28*(1+Inputs!B35)/Inputs!B36,0)*Inputs!B36 -> 920000
A35: Components valued separately (in addition to the business price)
A36: Quota liquor license (separate market) | B36: 0
A37: Real estate (from commercial BPO/CMA or appraisal) | B37: 0
A38: Inventory at cost, sold in addition to price | B38: 40000
A39: Total transaction value at asking | B39: =B33+SUM(B36:B38) -> 960000
A41: Implied metrics at asking price
A42: Asking price / weighted SDE | B42: =IF(B4=0,0,B33/B4) -> 2.6079899
A43: Asking price / weighted revenue | B43: =IF(B5=0,0,B33/B5) -> 0.45885287
A44: Asking price vs. asset floor | B44: =IF(B24=0,0,B33/B24) -> 2.2439024
A46: Not an appraisal. Prepared for pricing and marketing only. See README.

Sheet Buyer Test
A1: Buyer's Test — Debt-Service Coverage and Maximum Supportable Price
A2: Can an SBA buyer pay a market salary and service the debt at the target coverage ratio? If not, the price is wrong whatever the multiple says.
A4: Price tested
A5: Override price to test (leave blank to use the asking price)
A6: Price tested | B6: =IF(B5="",Valuation!B33,B5) -> 920000
A8: Sources of funds
A9: Buyer down payment | B9: =B6*Inputs!B24 -> 92000
A10: Seller note | B10: =B6*Inputs!B25 -> 92000
A11: Closing costs + working capital financed | B11: =Inputs!B30 -> 50000
A12: SBA 7(a) loan | B12: =B6-B9-B10+B11 -> 786000
A14: Annual debt service
A15: SBA loan | B15: =-PMT(Inputs!B28/12,Inputs!B29*12,B12)*12 -> 127270.69
A16: Seller note | B16: =-PMT(Inputs!B26/12,Inputs!B27*12,B10)*12 -> 21860.523
A17: Total annual debt service | B17: =B15+B16 -> 149131.21
A19: Coverage
A20: Weighted SDE | B20: =Recast!$G$29 -> 352762.1
A21: Less: buyer market salary | B21: =Inputs!B31 -> 100000
A22: Cash available for debt service | B22: =B20-B21 -> 252762.1
A23: Debt-service coverage ratio | B23: =IF(B17=0,0,B22/B17) -> 1.6948974
A24: Cushion after salary and debt service | B24: =B22-B17 -> 103630.89
A25: Cash-on-cash return on down payment | B25: =IF(B9=0,0,B24/B9) -> 1.1264227
A26: Result vs. target coverage | B26: =IF(B23>=Inputs!B32,"PASS","FAIL") -> PASS
A28: Maximum supportable price at target coverage
A29: Annual debt service the cash flow can carry | B29: =IF(Inputs!B32=0,0,B22/Inputs!B32) -> 202209.68
A30: Debt service per $1 of price (SBA share + seller-note share) | B30: =-PMT(Inputs!B28/12,Inputs!B29*12,1-Inputs!B24-Inputs!B25)*12-PMT(Inputs!B26/12,Inputs!B27*12,Inputs!B25)*12 -> 0.15329904
A31: Fixed debt service on financed closing costs | B31: =-PMT(Inputs!B28/12,Inputs!B29*12,Inputs!B30)*12 -> 8096.0998
A32: Maximum supportable price | B32: =IF(B30=0,0,(B29-B31)/B30) -> 1266241.4
A33: Asking price as % of maximum supportable | B33: =IF(B32=0,0,Valuation!B33/B32) -> 0.72655974
A35: Sensitivity — price vs. coverage
A36: Price factor | B36: Price | C36: SBA loan | D36: Seller note | E36: Total debt service | F36: DSCR | G36: Cushion | H36: Result
A37: 0.8 | B37: =$B$6*A37 -> 736000 | C37: =B37*(1-Inputs!$B$24-Inputs!$B$25)+Inputs!$B$30 -> 638800 | D37: =B37*Inputs!$B$25 -> 73600 | E37: =-PMT(Inputs!$B$28/12,Inputs!$B$29*12,C37)*12-PMT(Inputs!$B$26/12,Inputs!$B$27*12,D37)*12 -> 120924.19 | F37: =IF(E37=0,0,$B$22/E37) -> 2.0902526 | G37: =$B$22-E37 -> 131837.91 | H37: =IF(F37>=Inputs!$B$32,"PASS","FAIL") -> PASS
A38: 0.9 | B38: =$B$6*A38 -> 828000 | C38: =B38*(1-Inputs!$B$24-Inputs!$B$25)+Inputs!$B$30 -> 712400 | D38: =B38*Inputs!$B$25 -> 82800 | E38: =-PMT(Inputs!$B$28/12,Inputs!$B$29*12,C38)*12-PMT(Inputs!$B$26/12,Inputs!$B$27*12,D38)*12 -> 135027.7 | F38: =IF(E38=0,0,$B$22/E38) -> 1.8719277 | G38: =$B$22-E38 -> 117734.4 | H38: =IF(F38>=Inputs!$B$32,"PASS","FAIL") -> PASS
A39: 1 | B39: =$B$6*A39 -> 920000 | C39: =B39*(1-Inputs!$B$24-Inputs!$B$25)+Inputs!$B$30 -> 786000 | D39: =B39*Inputs!$B$25 -> 92000 | E39: =-PMT(Inputs!$B$28/12,Inputs!$B$29*12,C39)*12-PMT(Inputs!$B$26/12,Inputs!$B$27*12,D39)*12 -> 149131.21 | F39: =IF(E39=0,0,$B$22/E39) -> 1.6948974 | G39: =$B$22-E39 -> 103630.89 | H39: =IF(F39>=Inputs!$B$32,"PASS","FAIL") -> PASS
A40: 1.1 | B40: =$B$6*A40 -> 1012000 | C40: =B40*(1-Inputs!$B$24-Inputs!$B$25)+Inputs!$B$30 -> 859600 | D40: =B40*Inputs!$B$25 -> 101200 | E40: =-PMT(Inputs!$B$28/12,Inputs!$B$29*12,C40)*12-PMT(Inputs!$B$26/12,Inputs!$B$27*12,D40)*12 -> 163234.72 | F40: =IF(E40=0,0,$B$22/E40) -> 1.5484579 | G40: =$B$22-E40 -> 89527.377 | H40: =IF(F40>=Inputs!$B$32,"PASS","FAIL") -> PASS
A41: 1.2 | B41: =$B$6*A41 -> 1104000 | C41: =B41*(1-Inputs!$B$24-Inputs!$B$25)+Inputs!$B$30 -> 933200 | D41: =B41*Inputs!$B$25 -> 110400 | E41: =-PMT(Inputs!$B$28/12,Inputs!$B$29*12,C41)*12-PMT(Inputs!$B$26/12,Inputs!$B$27*12,D41)*12 -> 177338.23 | F41: =IF(E41=0,0,$B$22/E41) -> 1.4253108 | G41: =$B$22-E41 -> 75423.865 | H41: =IF(F41>=Inputs!$B$32,"PASS","FAIL") -> PASS
A42: 1.3 | B42: =$B$6*A42 -> 1196000 | C42: =B42*(1-Inputs!$B$24-Inputs!$B$25)+Inputs!$B$30 -> 1006800 | D42: =B42*Inputs!$B$25 -> 119600 | E42: =-PMT(Inputs!$B$28/12,Inputs!$B$29*12,C42)*12-PMT(Inputs!$B$26/12,Inputs!$B$27*12,D42)*12 -> 191441.75 | F42: =IF(E42=0,0,$B$22/E42) -> 1.3203082 | G42: =$B$22-E42 -> 61320.354 | H42: =IF(F42>=Inputs!$B$32,"PASS","FAIL") -> PASS

Sheet Screen
A1: Listing Screen — Qualification Scorecard
A2: Score each line 0 (red), 1 (yellow), or 2 (green). See playbook §1.2 for the criteria. Decision is computed below.
A4: No. | B4: Factor | C4: Score (0–2) | D4: Critical? | E4: Green (2) | F4: Yellow (1) | G4: Red (0) | H4: Note
A5: 1 | B5: Seller's Discretionary Earnings | C5: 2 | E5: ≥ $150K | F5: $75K–$150K | G5: < $75K
A6: 2 | B6: Books | C6: 2 | D6: Y | E6: Returns reconcile; deposits tie out | F6: Small explainable gaps | G6: Cash business claiming unreported income
A7: 3 | B7: Trend | C7: 2 | E7: Flat or rising 3 yrs | F7: One explained down year | G7: Declining 2+ yrs
A8: 4 | B8: Owner dependence | C8: 1 | E8: Manager in place; owner < 40 hrs | F8: Owner key but documented | G8: Owner is the business
A9: 5 | B9: Customer concentration | C9: 2 | E9: None > 10% | F9: Largest 10–25% | G9: One > 25% or non-assignable
A10: 6 | B10: Lease / premises | C10: 2 | E10: ≥ 5 yrs, assignable, market rent | F10: 2–5 yrs, cooperative landlord | G10: < 2 yrs / hostile / rent reset
A11: 7 | B11: Transferability of licenses | C11: 1 | E11: Transfer routinely | F11: Needs qualifier / DBPR approval | G11: Personal to owner
A12: 8 | B12: Legal standing | C12: 2 | D12: Y | E12: Active, no litigation, liens, taxes current | F12: Minor curable issues | G12: Litigation / unpaid DOR tax / liens
A13: 9 | B13: Staff | C13: 1 | E13: Key people staying; no misclassification | F13: One key person at risk | G13: Key person leaving / 1099 misclassification
A14: 10 | B14: Seller expectation vs. BOV range | C14: 2 | D14: Y | E14: Within 10% | F14: Within 25% | G14: Wants 2× and won't move
A15: 11 | B15: Motivation and timeline | C15: 2 | E15: Clear reason, 6–12 months, will transition | F15: Vague | G15: Testing the market / must close in 30 days
A16: 12 | B16: Industry outlook | C16: 2 | E16: Stable or growing locally | F16: Cyclical | G16: Structurally declining
B17: Total score (of 24) | C17: =SUM(C5:C16) -> 21
B18: Critical reds (books, legal standing, expectation gap) | C18: =SUMPRODUCT(--(D5:D16="Y"),--(C5:C16=0)) -> 0
B19: Decision | C19: =IF(C18>0,"DECLINE — critical red",IF(C17>=17,"LIST",IF(C17>=12,"EXIT-READINESS AUDIT FIRST","DECLINE — re-look in 12 months"))) -> LIST
